tinyredis.py
tinyredis-0.0.2.dist-info/LICENSE
tinyredis-0.0.2.dist-info/METADATA
tinyredis-0.0.2.dist-info/WHEEL
tinyredis-0.0.2.dist-info/top_level.txt
tinyredis-0.0.2.dist-info/RECORD
