Metadata-Version: 2.1
Name: tinyredis
Version: 0.0.2
Summary: Minimalist API for redis
Author-email: Jeremy Howard <info@fast.ai>
License: Apache License
Project-URL: Homepage, https://github.com/AnswerDotAI/tinyredis
Classifier: Development Status :: 3 - Alpha
Classifier: Intended Audience :: Developers
Classifier: License :: OSI Approved :: Apache Software License
Requires-Python: <4,>=3.7
License-File: LICENSE
Requires-Dist: fastcore
Requires-Dist: redis
